Metadata-Version: 2.0
Name: cs46-hartono-trees
Version: 1.0.0
Summary: A simple tree data structure implementation in Python, which covers Binary Search Trees, AVL Trees and Heaps.
Home-page: https://github.com/shartono17/trees
Author: Sabrina Hartono
Author-email: shartono21@students.claremontmckenna.edu
License: GPLv3
Platform: UNKNOWN
Classifier: Programming Language :: Python :: 3
Classifier: Programming Language :: Python :: 3.7
Requires-Dist: hypothesis
Requires-Dist: pytest
